API/BlockExplorerApi.py
API/__init__.py
DAGAPI/BlockExplorerApi.py
DAGAPI/__init__.py
examples/GettingStart.py
examples/__init__.py
DagApi-0.1.2.dist-info/LICENSE
DagApi-0.1.2.dist-info/METADATA
DagApi-0.1.2.dist-info/WHEEL
DagApi-0.1.2.dist-info/top_level.txt
DagApi-0.1.2.dist-info/RECORD
