Metadata-Version: 2.1
Name: DagApi
Version: 0.1.2
Summary: Python API for work with Constellation Network
Home-page: https://github.com/Pena-Co-Ltd/dag-api-python
Author: Ivan Radaev
Author-email: radaevir@gmail.com
License: MIT
Keywords: Python API Constellation DAG
Platform: UNKNOWN
Classifier: Intended Audience :: Developers
Classifier: License :: OSI Approved :: MIT License
Classifier: Operating System :: OS Independent
Classifier: Programming Language :: Python :: 3
Classifier: Programming Language :: Python :: 3.6
Classifier: Programming Language :: Python :: 3.7
Classifier: Programming Language :: Python
Classifier: Topic :: Software Development :: Libraries :: Python Modules
